fryer/__init__.py
fryer/fryer.py
fryer/helpers.py
fryer/main.py
image_fryer-1.0.0.dist-info/LICENSE
image_fryer-1.0.0.dist-info/METADATA
image_fryer-1.0.0.dist-info/WHEEL
image_fryer-1.0.0.dist-info/top_level.txt
image_fryer-1.0.0.dist-info/RECORD
