Metadata-Version: 2.1
Name: image-fryer
Version: 1.0.0
Summary: Your favorite deep frying image library
Home-page: https://github.com/NahuLD/image-fryer
Author: NahuLD
Author-email: contact@nahu.me
License: MIT
Platform: UNKNOWN
Classifier: Development Status :: 5 - Production/Stable
Classifier: License :: OSI Approved :: MIT License
Classifier: Intended Audience :: Developers
Classifier: Natural Language :: English
Classifier: Operating System :: OS Independent
Classifier: Programming Language :: Python :: 3 :: Only
Classifier: Topic :: Internet
Classifier: Topic :: Software Development :: Libraries
Classifier: Topic :: Software Development :: Libraries :: Python Modules
Classifier: Topic :: Utilities
Requires-Dist: Pillow (==6.2.0)
Requires-Dist: opencv-python (==4.1.2.30)
Requires-Dist: numpy (==1.17.4)
